[
    {
        "created": "20230926010148000",
        "creator": "马不前",
        "title": "λ:/thoughts-memo-translation-main/other/A Mathematician's Lament",
        "text": "# 数学家的哀歌\r\n\r\n作者：Paul Lockhart\r\n\r\n## 数学与文化\r\n\r\n[img [image|./01-triangle-box.png]]\r\n\r\n[img [image|./02-chopped-triangle.png]]\r\n\r\n***",
        "type": "text/markdown",
        "caption": " 数学家的哀歌\r",
        "modified": "20230930171250227",
        "modifier": "马不前",
        "obvault": "thoughts-memo-translation-main",
        "original-title": "A Mathematician's Lament"
    }
]