[
    {
        "created": "20230926010148000",
        "creator": "马不前",
        "title": "λ:/thoughts-memo-translation-main/README",
        "text": "# Thoughts 汉化作品系列简介\r\n\r\n- Wozniak\r\n  - FAQ：回答读者问题\r\n  - Glossary：专有名词解释\r\n  - Help：SuperMemo 使用帮助\r\n  - Myth：粉碎谣言\r\n  - Prose：长篇大论\r\n    - Problem of School：锐评学校教育\r\n    - Science of Sleep：睡眠科学\r\n    - Other：未分类\r\n  - Reference：参考资料\r\n\r\n- Refold\r\n  - 语言学习导航\r\n\r\n- Gray\r\n  - 家庭教育与学校教育\r\n\r\n- Andy\r\n  - Outline：笔记主题大纲\r\n  - Handle：概念抓手（黑话）\r\n  - Prose：长文，部分为 Patreon 付费内容\r\n  - Note： 常青笔记\r\n    - Chunk 组块\r\n    - Cognitive scaffold 认知脚手架\r\n    - Enabling environment 赋能环境\r\n    - Enacted experience 情景体验\r\n    - Evergreen note 常青笔记\r\n    - Inbox 收件箱（这个话题）\r\n    - Knowledge work 知识工作\r\n    - Software 软件介绍\r\n    - Mnemonic medium 助记媒介\r\n    - Spaced repetition 间隔重复\r\n    - Tools for thought 思想工具\r\n\r\n- Rice\r\n  - SRS 在数学中的应用\r\n  - 教育相关话题\r\n\r\n- Krashen\r\n  - 二语习得理论\r\n",
        "type": "text/markdown",
        "caption": " Thoughts 汉化作品系列简介\r",
        "modified": "20230930171250227",
        "modifier": "马不前",
        "obvault": "thoughts-memo-translation-main",
        "original-title": "README"
    }
]