[
    {
        "created": "20230926010148000",
        "creator": "马不前",
        "title": "λ:/thoughts-memo-translation-main/andy/outline/Let ideas and beliefs emerge organically",
        "text": "# 让思想和信念有机地涌现\r\n\r\n原文：[Let ideas and beliefs emerge organically (andymatuschak.org)](https://notes.andymatuschak.org/z5uSCvx3W2GdzBVhWAAXrrCcykJ8SHimdJzg7)\r\n\r\n谨防先入为主的观念。[独立思考](https://notes.andymatuschak.org/z4enRPbLXdD8X8hCfVjaRkcGkronvhcfrgSQw)。\r\n\r\n- 通过使用已有作品，更快地完成现在的作品\r\n\r\n  - [常青笔记写作是知识工作的基本单位](https://notes.andymatuschak.org/z3SjnvsB5aR2ddsycyXofbYR7fCxo7RmKW2be)\r\n\r\n    - [在写作时创建推测性大纲](https://notes.andymatuschak.org/z2uXyfV67dnWLUKg1iDbsrHk3DGjtNWTxSTah)\r\n\r\n  - [可执行的写作策略](https://notes.andymatuschak.org/z3PBVkZ2SvsAgFXkjHsycBeyS6Cw1QXf7kcD8)\r\n\r\n- 认识论、原创性\r\n\r\n  - [使用笔记来避免先入为主的结论](https://notes.andymatuschak.org/z6Mx6PrJjGCf2akGM9pvoZ5Nk3EozcZcc9zHx)\r\n\r\n  - [卓越洞见从既往的所思所想中涌现](https://notes.andymatuschak.org/zSn7SX7yMtnh1ZCQEG44TJoxrH7Udpm9oeEm)\r\n\r\n    - [头脑风暴往往可以替代缺位的见解积累系统](https://notes.andymatuschak.org/z5cVs9BKLJsCYifhYBstAEKuZ8driDzLB3gFd)\r\n\r\n  - [优先建立信息间的联系来分类，而非使用层级式分类法](https://notes.andymatuschak.org/z29hLZHiVt7W2uss2uMpSZquAX5T6vaeSF6Cy)\r\n\r\n  - [常青笔记是发展大胆想法的安全场所](https://notes.andymatuschak.org/z8RTzukqNLKFXzqLwx25HrUrg5E5jiziGznWB)\r\n\r\n- 士气：\r\n\r\n  - 对自己真实的兴趣和想法做出反应，而不是想着「我应该写 X」\r\n\r\n  - 不再有「我应该写什么？」的想法",
        "type": "text/markdown",
        "caption": " 让思想和信念有机地涌现\r",
        "modified": "20230930171250225",
        "modifier": "马不前",
        "obvault": "thoughts-memo-translation-main",
        "original-title": "Let ideas and beliefs emerge organically"
    }
]